jazzhands/__init__.py
jazzhands/conftest.py
jazzhands/utils.py
jazzhands/version.py
jazzhands/wavelets.py
jazzhands/data/README.rst
jazzhands/data/benchmarking.ipynb
jazzhands/extern/__init__.py
jazzhands/tests/__init__.py
jazzhands/tests/test_utils.py
jazzhands/tests/test_wavelets.py
jazz_hands-0.0.3.dist-info/LICENSE.rst
jazz_hands-0.0.3.dist-info/METADATA
jazz_hands-0.0.3.dist-info/WHEEL
jazz_hands-0.0.3.dist-info/entry_points.txt
jazz_hands-0.0.3.dist-info/top_level.txt
jazz_hands-0.0.3.dist-info/RECORD
