Metadata-Version: 2.1
Name: jazz-hands
Version: 0.0.3
Summary: Your one-stop-shop for quick computations with wavelets (aka little waves, aka jazz hands) on irregularly sampled data.
Home-page: https://jazzhands.readthedocs.io/en/latest/index.html
Author: Trevor Dorn-Wallenstein et al.
Author-email: tzdw@uw.edu
License: BSD 3-Clause
Platform: UNKNOWN
Requires-Python: >=3.6
Requires-Dist: extension-helpers (>=0.1)
Requires-Dist: numpy (>=1.19.1)
Requires-Dist: scipy (>=1.5.2)
Requires-Dist: astropy
Requires-Dist: tqdm
Requires-Dist: matplotlib
Provides-Extra: docs
Requires-Dist: sphinx-astropy ; extra == 'docs'
Provides-Extra: test
Requires-Dist: pytest-astropy ; extra == 'test'
